betterbib/__init__.py
betterbib/_cache.py
betterbib/_console.py
betterbib/_helpers.py
betterbib/_journal_names.py
betterbib/_lang.py
betterbib/_library.py
betterbib/_sync.py
betterbib/_tex_parser.py
betterbib/_tools.py
betterbib/errors.py
betterbib/cli/__init__.py
betterbib/cli/_convert.py
betterbib/cli/_doi_to.py
betterbib/cli/_format.py
betterbib/cli/_main.py
betterbib/cli/_sync.py
betterbib/data/capit.json
betterbib/data/journals.json
betterbib/io/__init__.py
betterbib/io/_main.py
betterbib/io/biblatex.py
betterbib/io/bibtex.py
betterbib/io/csl_json.py
betterbib/io/ris.py
betterbib/sources/__init__.py
betterbib/sources/_helpers.py
betterbib/sources/_main.py
betterbib/sources/arxiv.py
betterbib/sources/crossref.py
betterbib/sources/dblp.py
betterbib/sources/pubmed.py
betterbib/sources/zenodo.py
betterbib-7.5.25.dist-info/METADATA
betterbib-7.5.25.dist-info/WHEEL
betterbib-7.5.25.dist-info/entry_points.txt
betterbib-7.5.25.dist-info/top_level.txt
betterbib-7.5.25.dist-info/RECORD
