Metadata-Version: 2.4
Name: betterbib
Version: 7.5.25
Summary: Better bibliography data
Author-email: Nico Schlömer <nico.schloemer@gmail.com>
Project-URL: Homepage, https://github.com/texworld/betterbib
Project-URL: Issues, https://github.com/texworld/betterbib/issues
Keywords: bibtex,latex
Classifier: Development Status :: 5 - Production/Stable
Classifier: Operating System :: OS Independent
Classifier: Programming Language :: Python :: 3 :: Only
Classifier: Programming Language :: Python :: 3.10
Classifier: Programming Language :: Python :: 3.11
Classifier: Programming Language :: Python :: 3.12
Classifier: Programming Language :: Python :: 3.13
Classifier: Topic :: Text Editors :: Text Processing
Classifier: Topic :: Text Processing
Classifier: Topic :: Text Processing :: Markup
Classifier: Topic :: Text Processing :: Markup :: LaTeX
Classifier: Topic :: Utilities
Requires-Python: >=3.10
Requires-Dist: bibtexparser>=2.0.0b8
Requires-Dist: platformdirs>=3.2
Requires-Dist: pylatexenc>=2.10
Requires-Dist: python-package-info>=0.0.10
Requires-Dist: requests>=2
Requires-Dist: requests-cache>=1
Requires-Dist: rich>=9.4
Requires-Dist: rich-argparse>=1
Requires-Dist: stonefish-license-manager>=0.5.31
Requires-Dist: tomli>=2; python_version < "3.11"
Requires-Dist: xmltodict>=0.14
Requires-Dist: stonefish_runtime>=0.3.3
